{
  "services": [
    {
      "category": "Зони росту волосся на обличчі",
      "items": [
        { "service": "60 хвилин", "price": "800 грн" },
        { "service": "30 хвилин", "price": "400 грн" },
        { "service": "1 хвилина", "price": "13.50 грн" }
      ]
    },
    {
      "category": "Зони росту волосся на тілі",
      "items": [
        { "service": "60 хвилин", "price": "700 грн" },
        { "service": "30 хвилин", "price": "350 грн" },
        { "service": "1 хвилина", "price": "12.00 грн" }
      ]
    },
    {
      "category": null,
      "items": [
        { "service": "Голка-зонд", "price": "100 грн" },
        { "service": "Аплікаційна анестезія", "price": "від 150 грн" },
        { "service": "Ін'єкційна анестезія", "price": "від 200 грн" },
        { "service": "Тест-драйв (будь-якої зони)", "price": "100 грн" }
      ]
    }
  ]
}
